xsxl-0.1.0.dist-info/METADATA
xsxl-0.1.0.dist-info/WHEEL
xsxl/__init__.py
xsxl/__init__.pyi
xsxl/_core.pyd
xsxl-0.1.0.dist-info/RECORD
