Metadata-Version: 2.4
Name: xsxl
Version: 0.1.0
Classifier: Development Status :: 3 - Alpha
Classifier: Intended Audience :: Developers
Classifier: License :: OSI Approved :: MIT License
Classifier: License :: OSI Approved :: Apache Software License
Classifier: Programming Language :: Rust
Classifier: Programming Language :: Python :: Implementation :: CPython
Classifier: Programming Language :: Python :: 3
Classifier: Programming Language :: Python :: 3.9
Classifier: Programming Language :: Python :: 3.10
Classifier: Programming Language :: Python :: 3.11
Classifier: Programming Language :: Python :: 3.12
Classifier: Topic :: Software Development :: Libraries
Classifier: Topic :: File Formats
Requires-Dist: pyarrow>=10.0
Requires-Dist: pandas>=1.5 ; extra == 'pandas'
Requires-Dist: polars>=0.18 ; extra == 'polars'
Requires-Dist: pytest>=7.0 ; extra == 'dev'
Requires-Dist: pandas>=1.5 ; extra == 'dev'
Requires-Dist: polars>=0.18 ; extra == 'dev'
Requires-Dist: maturin>=1.0 ; extra == 'dev'
Provides-Extra: pandas
Provides-Extra: polars
Provides-Extra: dev
Summary: High-performance Python library for streaming Excel (XLSX) data to Apache Arrow format
Keywords: excel,xlsx,arrow,parser,etl
Author-email: Your Name <your.email@example.com>
License: MIT OR Apache-2.0
Requires-Python: >=3.9
Project-URL: Homepage, https://github.com/yourusername/xsxl
Project-URL: Repository, https://github.com/yourusername/xsxl
Project-URL: Documentation, https://xsxl.readthedocs.io
